adafruit_circuitpython_display_text-4.0.2.dist-info/licenses/LICENSE
adafruit_display_text/__init__.py
adafruit_display_text/bitmap_label.py
adafruit_display_text/label.py
adafruit_display_text/outlined_label.py
adafruit_display_text/scrolling_label.py
adafruit_display_text/text_box.py
adafruit_circuitpython_display_text-4.0.2.dist-info/METADATA
adafruit_circuitpython_display_text-4.0.2.dist-info/WHEEL
adafruit_circuitpython_display_text-4.0.2.dist-info/top_level.txt
adafruit_circuitpython_display_text-4.0.2.dist-info/RECORD
