Metadata-Version: 2.4
Name: adafruit-circuitpython-display-text
Version: 4.0.2
Summary: Displays text using CircuitPython's displayio.
Author-email: Adafruit Industries <circuitpython@adafruit.com>
License: MIT
Project-URL: Homepage, https://github.com/adafruit/Adafruit_CircuitPython_Display_Text
Keywords: adafruit,blinka,circuitpython,micropython,bitmap,fonts,text,display,tft,lcd,displayio
Classifier: Intended Audience :: Developers
Classifier: Topic :: Software Development :: Libraries
Classifier: Topic :: Software Development :: Embedded Systems
Classifier: Topic :: System :: Hardware
Classifier: License :: OSI Approved :: MIT License
Classifier: Programming Language :: Python :: 3
License-File: LICENSE
Requires-Dist: Adafruit-Blinka-displayio>=0.10.2
Requires-Dist: Adafruit-Blinka
Requires-Dist: adafruit-circuitpython-bitmap-font
Requires-Dist: adafruit-circuitpython-ticks
Provides-Extra: optional
Dynamic: license-file
